{
    "day": [
        {
            "id": "100076191971607",
            "n": 18
        },
        {
            "id": "100093189680360",
            "n": 33
        },
        {
            "id": "100095402741665",
            "n": 2
        },
        {
            "id": "100068247970181",
            "n": 28
        },
        {
            "id": "100070868528461",
            "n": 11
        },
        {
            "id": "100091244569218",
            "n": 80
        },
        {
            "id": "100079217535225",
            "n": 4
        },
        {
            "id": "100081608606870",
            "n": 23
        },
        {
            "id": "100085867673904",
            "n": 39
        },
        {
            "id": "100090271661181",
            "n": 6
        },
        {
            "id": "100068244259535",
            "n": 5
        },
        {
            "id": "100094014420311",
            "n": 39
        },
        {
            "id": "100089253831849",
            "n": 9
        },
        {
            "id": "100075555436177",
            "n": 16
        },
        {
            "id": "61555244560417",
            "n": 8
        },
        {
            "id": "100075861292733",
            "n": 23
        },
        {
            "id": "100074385548699",
            "n": 45
        },
        {
            "id": "100051780603376",
            "n": 7
        },
        {
            "id": "61556917214894",
            "n": 2
        },
        {
            "id": "100087983057950",
            "n": 5
        },
        {
            "id": "100034085370847",
            "n": 22
        },
        {
            "id": "61555801534618",
            "n": 19
        },
        {
            "id": "100072934671646",
            "n": 40
        },
        {
            "id": "100084449340981",
            "n": 70
        },
        {
            "id": "100062415288509",
            "n": 7
        },
        {
            "id": "100058338471476",
            "n": 40
        },
        {
            "id": "100091074853072",
            "n": 21
        },
        {
            "id": "100077370174503",
            "n": 4
        },
        {
            "id": "100050498023529",
            "n": 19
        },
        {
            "id": "100082201059512",
            "n": 8
        },
        {
            "id": "100071906074779",
            "n": 3
        },
        {
            "id": "100076003105276",
            "n": 2
        },
        {
            "id": "100071785706806",
            "n": 2
        }
    ],
    "week": [
        {
            "id": "100076191971607",
            "n": 18
        },
        {
            "id": "100093189680360",
            "n": 33
        },
        {
            "id": "100095402741665",
            "n": 2
        },
        {
            "id": "100068247970181",
            "n": 28
        },
        {
            "id": "100070868528461",
            "n": 11
        },
        {
            "id": "100091244569218",
            "n": 80
        },
        {
            "id": "100079217535225",
            "n": 4
        },
        {
            "id": "100081608606870",
            "n": 23
        },
        {
            "id": "100085867673904",
            "n": 39
        },
        {
            "id": "100090271661181",
            "n": 6
        },
        {
            "id": "100068244259535",
            "n": 5
        },
        {
            "id": "100094014420311",
            "n": 39
        },
        {
            "id": "100089253831849",
            "n": 9
        },
        {
            "id": "100075555436177",
            "n": 16
        },
        {
            "id": "61555244560417",
            "n": 8
        },
        {
            "id": "100075861292733",
            "n": 23
        },
        {
            "id": "100074385548699",
            "n": 45
        },
        {
            "id": "100051780603376",
            "n": 7
        },
        {
            "id": "61556917214894",
            "n": 2
        },
        {
            "id": "100087983057950",
            "n": 5
        },
        {
            "id": "100034085370847",
            "n": 22
        },
        {
            "id": "61555801534618",
            "n": 19
        },
        {
            "id": "100072934671646",
            "n": 40
        },
        {
            "id": "100084449340981",
            "n": 70
        },
        {
            "id": "100062415288509",
            "n": 7
        },
        {
            "id": "100058338471476",
            "n": 40
        },
        {
            "id": "100091074853072",
            "n": 21
        },
        {
            "id": "100077370174503",
            "n": 4
        },
        {
            "id": "100050498023529",
            "n": 19
        },
        {
            "id": "100082201059512",
            "n": 8
        },
        {
            "id": "100071906074779",
            "n": 3
        },
        {
            "id": "100076003105276",
            "n": 2
        },
        {
            "id": "100071785706806",
            "n": 2
        }
    ],
    "all": [
        {
            "id": "100076191971607",
            "n": 18
        },
        {
            "id": "100093189680360",
            "n": 33
        },
        {
            "id": "100095402741665",
            "n": 2
        },
        {
            "id": "100068247970181",
            "n": 28
        },
        {
            "id": "100070868528461",
            "n": 11
        },
        {
            "id": "100091244569218",
            "n": 80
        },
        {
            "id": "100079217535225",
            "n": 4
        },
        {
            "id": "100081608606870",
            "n": 23
        },
        {
            "id": "100085867673904",
            "n": 39
        },
        {
            "id": "100090271661181",
            "n": 6
        },
        {
            "id": "100068244259535",
            "n": 5
        },
        {
            "id": "100094014420311",
            "n": 39
        },
        {
            "id": "100089253831849",
            "n": 9
        },
        {
            "id": "100075555436177",
            "n": 16
        },
        {
            "id": "61555244560417",
            "n": 8
        },
        {
            "id": "100075861292733",
            "n": 23
        },
        {
            "id": "100074385548699",
            "n": 45
        },
        {
            "id": "100051780603376",
            "n": 7
        },
        {
            "id": "61556917214894",
            "n": 2
        },
        {
            "id": "100087983057950",
            "n": 5
        },
        {
            "id": "100034085370847",
            "n": 22
        },
        {
            "id": "61555801534618",
            "n": 19
        },
        {
            "id": "100072934671646",
            "n": 40
        },
        {
            "id": "100084449340981",
            "n": 70
        },
        {
            "id": "100062415288509",
            "n": 7
        },
        {
            "id": "100058338471476",
            "n": 40
        },
        {
            "id": "100091074853072",
            "n": 21
        },
        {
            "id": "100077370174503",
            "n": 4
        },
        {
            "id": "100050498023529",
            "n": 19
        },
        {
            "id": "100082201059512",
            "n": 8
        },
        {
            "id": "100071906074779",
            "n": 3
        },
        {
            "id": "100076003105276",
            "n": 2
        },
        {
            "id": "100071785706806",
            "n": 2
        }
    ]
}